{"is_source_file": true, "format": "Dart", "description": "This file defines a Flutter widget for creating and editing notes, including UI components and associated logic for saving notes via a provider.", "external_files": ["../models/note.dart", "../providers/notes_provider.dart"], "external_methods": ["context.read<NotesProvider>()", "provider.addNote", "provider.editNote", "Navigator.of(context).pop()"], "published": [], "classes": [{"name": "NoteEditorScreen", "description": "A StatefulWidget that provides a screen for creating or editing a note."}, {"name": "_NoteEditorScreenState", "description": "The state class managing the logic and UI of the NoteEditorScreen, including text controllers and save operation."}], "methods": [{"name": "initState", "description": "Initializes the state; populates text controllers if editing an existing note."}, {"name": "dispose", "description": "Disposes of text controllers to free resources."}, {"name": "_save", "description": "Handles the save operation, updating or creating a note via the provider."}, {"name": "build", "description": "Builds the widget tree for the note editor screen, including input fields and save button."}], "calls": ["setState", "context.read", "provider.addNote", "provider.editNote", "Navigator.of(context).pop"], "search-terms": ["note editor", "Flutter note creation", "notes provider", "TextEditingController", "save note"], "state": 2, "file_id": 26, "knowledge_revision": 58, "git_revision": "", "hash": "437e4f8e81216026d65c476bc9a85452", "format-version": 4, "code-base-name": "notes_frontend", "filename": "notes_frontend/lib/screens/note_editor_screen.dart", "revision_history": [{"58": ""}]}